[
    {
      "start": "Coimbatore Junction",
      "end": "Gandhipuram Bus Stand",
      "routes": [
        {
          "timeLimit": 10,
          "coords": [
            [11.0008, 76.9664],
            [11.0055, 76.9681],
            [11.0182, 76.9787]
          ]
        },
        {
          "timeLimit": 20,
          "coords": [
            [11.0008, 76.9664],
            [11.0022, 76.9675],
            [11.0068, 76.9699],
            [11.0125, 76.9753],
            [11.0182, 76.9787]
          ]
        }
      ]
    },
    {
      "start": "Ukkadam Bus Stand",
      "end": "Peelamedu",
      "routes": [
        {
          "timeLimit": 15,
          "coords": [
            [10.9989, 76.9572],
            [11.0123, 76.9728],
            [11.0286, 76.9854]
          ]
        },
        {
          "timeLimit": 25,
          "coords": [
            [10.9989, 76.9572],
            [11.0050, 76.9650],
            [11.0123, 76.9728],
            [11.0220, 76.9800],
            [11.0286, 76.9854]
          ]
        }
      ]
    }
  ]
  